LICENSE.txt
README.md
setup.cfg
setup.py
blitzcrank/Blitzcrank.py
blitzcrank/__init__.py
blitzcrank.egg-info/PKG-INFO
blitzcrank.egg-info/SOURCES.txt
blitzcrank.egg-info/dependency_links.txt
blitzcrank.egg-info/requires.txt
blitzcrank.egg-info/top_level.txt
blitzcrank/apis/__init__.py
blitzcrank/apis/champion.py
blitzcrank/apis/champion_mastery.py
blitzcrank/apis/item.py
blitzcrank/apis/league.py
blitzcrank/apis/match.py
blitzcrank/apis/summoner.py
blitzcrank/tests/__init__.py
blitzcrank/tests/test_champion_endpoint.py
blitzcrank/tests/test_league_endpoint.py
blitzcrank/tests/test_match_endpoint.py
blitzcrank/tests/test_rate_limiting.py
blitzcrank/tests/test_summoner_endpoint.py
blitzcrank/util/__init__.py
blitzcrank/util/session.py