Metadata-Version: 2.1
Name: blitzcrank
Version: 0.0.1
Summary: The Riot API in Python, made easy.
Home-page: https://github.com/samhine/blitzcrank
Author: Samuel Hine
Author-email: sam.hine27@gmail.com
License: MIT
Download-URL: https://github.com/samhine/blitzcrank/archive/refs/tags/0.0.1.tar.gz
Keywords: PYTHON,RIOT,API
Platform: UNKNOWN
Classifier: Development Status :: 4 - Beta
Classifier: Intended Audience :: Developers
Classifier: Topic :: Software Development :: Build Tools
Classifier: License :: OSI Approved :: MIT License
Classifier: Programming Language :: Python :: 3.7
License-File: LICENSE.txt
